metric_builder/__init__.py
metric_builder/metric.py
metric_builder/readers.py
metric_builder/template_filters.py
metric_builder-2.1.4.4.dist-info/LICENSE
metric_builder-2.1.4.4.dist-info/METADATA
metric_builder-2.1.4.4.dist-info/WHEEL
metric_builder-2.1.4.4.dist-info/top_level.txt
metric_builder-2.1.4.4.dist-info/RECORD
