Metadata-Version: 2.1
Name: metric-builder
Version: 2.1.4.4
Summary: Utility for building templated metric extraction queries that can be traversed through time.
Home-page: UNKNOWN
Author: Philip Perold
Author-email: philip@spatialedge.co.za
License: UNKNOWN
Platform: UNKNOWN
Classifier: Environment :: Console
Classifier: Intended Audience :: Developers
Classifier: License :: OSI Approved :: Apache Software License
Classifier: Programming Language :: Python :: 3
Classifier: Topic :: Utilities
License-File: LICENSE
Requires-Dist: Jinja2 (>=2.11.3)
